panoptes/__init__.py
panoptes/aws/__init__.py
panoptes/aws/analysis.py
panoptes/aws/attached.py
panoptes/aws/authentication.py
panoptes/aws/exceptions.py
panoptes/aws/output.py
panoptes/aws/whitelist.py
panoptes/cli/__init__.py
panoptes/cli/aws.py
panoptes/cli/gcp.py
panoptes/generic/__init__.py
panoptes/generic/helpers.py
panoptes/generic/output.py
panoptes/panoptesctl.py
panoptes-0.5.0.dist-info/entry_points.txt
panoptes-0.5.0.dist-info/LICENSE
panoptes-0.5.0.dist-info/WHEEL
panoptes-0.5.0.dist-info/METADATA
panoptes-0.5.0.dist-info/RECORD
