Metadata-Version: 2.1
Name: panoptes
Version: 0.5.0
Summary: The multi cloud security group analyzer
Home-page: https://github.com/tioxy/panoptes
License: Apache-2.0
Keywords: panoptes,aws,security,analysis,cloud
Author: Gabriel Tiossi
Author-email: gabrieltiossi@gmail.com
Requires-Python: >=3.7,<4.0
Classifier: License :: OSI Approved :: Apache Software License
Classifier: Programming Language :: Python :: 3
Classifier: Programming Language :: Python :: 3.7
Classifier: Programming Language :: Python :: 3.8
Requires-Dist: Jinja2 (>=2.11,<3.0)
Requires-Dist: PyYAML (>=5.3,<6.0)
Requires-Dist: boto3 (>=1.14,<2.0)
Requires-Dist: click (>=7.1,<8.0)
Requires-Dist: colorama (>=0.4.3,<0.5.0)
Project-URL: Documentation, https://github.com/tioxy/panoptes/tree/master/docs
Project-URL: Repository, https://github.com/tioxy/panoptes
